siasearch/__init__.py
siasearch/mixins.py
siasearch/results.py
siasearch/segment.py
siasearch/session.py
siasearch/siasearch.py
siasearch/urls.py
siasearch/utils.py
siasearch-0.0.2.dist-info/LICENSE
siasearch-0.0.2.dist-info/METADATA
siasearch-0.0.2.dist-info/WHEEL
siasearch-0.0.2.dist-info/top_level.txt
siasearch-0.0.2.dist-info/RECORD
