Metadata-Version: 2.1
Name: siasearch
Version: 0.0.2
Summary: SDK for SiaSearch platform API
Home-page: https://github.com/merantix/siasearch_python_sdk
Author: Timofey Molchanov
Author-email: timofey.molchanov@merantix.com
License: UNKNOWN
Platform: UNKNOWN
Classifier: Programming Language :: Python :: 3
Classifier: License :: OSI Approved :: MIT License
Classifier: Operating System :: OS Independent
Requires-Python: >=3.6
Requires-Dist: pandas
Requires-Dist: matplotlib
Requires-Dist: scikit-image
Requires-Dist: requests
